bert_fine_tuning_text_classifier_lux/__init__.py
bert_fine_tuning_text_classifier_lux/text_classification_model.py
bert_fine_tuning_text_classifier_lux-0.2.3.dist-info/LICENSE
bert_fine_tuning_text_classifier_lux-0.2.3.dist-info/METADATA
bert_fine_tuning_text_classifier_lux-0.2.3.dist-info/WHEEL
bert_fine_tuning_text_classifier_lux-0.2.3.dist-info/top_level.txt
bert_fine_tuning_text_classifier_lux-0.2.3.dist-info/RECORD
